{"title": {"cop": "Ⲙⲁⲣⲉⲛⲟⲩⲱϣⲧ ⲙ̀Ⲡⲉⲛⲥⲱⲧⲏⲣ", "eng": "The Annual Gospel Response", "ara": " (مرد الإنجيل (سنوي "}, "items": [{"user": {"cop": "Ⲡⲓⲗⲁⲟⲥ", "eng": "People", "ara": "الشعب "}, "text": {"cop": ["Ⲙⲁⲣⲉⲛⲟⲩⲱϣⲧ ⲙ̀Ⲡⲉⲛⲥⲱⲧⲏⲣ: Ⲡⲓⲙⲁⲓⲣⲱⲙⲓ ⲛ̀ⲁ̀ⲅⲁⲑⲟⲥ: ϫⲉ ⲛ̀ⲑⲟϥ ⲁϥϣⲉⲛϩⲏⲧ ϧⲁⲣⲟⲛ: ⲁϥⲓ̀ ⲟⲩⲟϩ ⲁϥⲥⲱϯ ⲙ̀ⲙⲟⲛ.", "̀Ⲁⲣⲓⲡ̀ⲣⲉⲥⲃⲉⲩⲓⲛ ⲉ̀ϩ̀ⲣⲏⲓ ⲉ̀ϫⲱⲛ: ⲱ̀ ⲧⲉⲛϭⲟⲓⲥ ⲛ̀ⲛⲏⲃ ⲧⲏⲣⲉⲛ Ϯⲑⲉⲟ̀ⲧⲟⲕⲟⲥ: Ⲙⲁⲣⲓⲁ Ⲑ̀ⲙⲁⲩ ⲙ̀Ⲡⲉⲛⲥⲱⲧⲏⲣ: ⲛ̀ⲧⲉϥⲭⲁ ⲛⲉⲛⲛⲟⲃⲓ ⲛⲁⲛ ⲉ̀ⲃⲟⲗ.", "Ϫⲉ ϥ̀ⲥ̀ⲙⲁⲣⲱⲟⲩⲧ ⲛ̀ϫⲉ Ⲫ̀ⲓⲱⲧ ⲛⲉⲙ Ⲡ̀ϣⲏⲣⲓ: ⲛⲉⲙ Ⲡⲓⲡ̀ⲛⲉⲩⲙⲁ Ⲉⲑⲟⲩⲁⲃ: Ϯⲧ̀ⲣⲓⲁⲥ ⲉⲧϫⲏⲕ ⲉ̀ⲃⲟⲗ: ⲧⲉⲛⲟⲩⲱϣⲧ ⲙ̀ⲙⲟⲥ ⲧⲉⲛϯⲱ̀ⲟⲩ ⲛⲁⲥ."], "eng": ["Let us worship our Savior, the Good One and Lover of Mankind, for He had compassion on us and has come and saved us", "Intercede on our behalf, O Lady of us all, the Theotokos, Mary, the mother of our Savior, that He may forgive us our sins.", "Blessed be the Father and the Son / and the Holy Spirit / the perfect Trinity / we worship Him and glorify Him."], "ara": [" .فلنسجد لمخلصنا، محب البشر الصالح، لأنه تراءف علينا، أتى وخلصنا ", " .إشفعي فينا أمام الرب، يا سيدتنا كلنا السيدة والدة الإله، مريم أم مخلصنا، ليغفر لنا خطايانا ", " .لأنه مبارك الآب والإبن، والروح القدس، الثالوث الكامل، نسجد له ونمجده "]}}]}
